ohmytokencount/__init__.py
ohmytokencount-0.1.2.dist-info/WHEEL
ohmytokencount-0.1.2.dist-info/entry_points.txt
ohmytokencount-0.1.2.dist-info/METADATA
ohmytokencount-0.1.2.dist-info/RECORD
