Metadata-Version: 2.3
Name: ohmytokencount
Version: 0.1.2
Summary: Add your description here
Author: ZhuangYumin
Author-email: ZhuangYumin <zymx@pm.me>
Requires-Dist: tiktoken>=0.11.0
Requires-Python: >=3.12.11
